LICENSE
MANIFEST.in
README.rst
setup.cfg
setup.py
cgen/__init__.py
cgen/cuda.py
cgen/ispc.py
cgen/mapper.py
cgen/opencl.py
cgen/version.py
cgen.egg-info/PKG-INFO
cgen.egg-info/SOURCES.txt
cgen.egg-info/dependency_links.txt
cgen.egg-info/requires.txt
cgen.egg-info/top_level.txt
doc/Makefile
doc/source/cgen.rst
doc/source/conf.py
doc/source/faq.rst
doc/source/index.rst
test/test_cgen.py