Metadata-Version: 1.1
Name: cgen
Version: 2020.1
Summary: C/C++ source generation from an AST
Home-page: http://documen.tician.de/cgen/
Author: Andreas Kloeckner
Author-email: inform@tiker.net
License: MIT
Platform: UNKNOWN
Classifier: Development Status :: 4 - Beta
Classifier: Intended Audience :: Developers
Classifier: Intended Audience :: Other Audience
Classifier: Intended Audience :: Science/Research
Classifier: License :: OSI Approved :: MIT License
Classifier: Natural Language :: English
Classifier: Programming Language :: Python
Classifier: Topic :: Scientific/Engineering
Classifier: Topic :: Software Development :: Libraries
Classifier: Topic :: Utilities
